flatflow/_C.cpython-311-x86_64-linux-gnu.so
flatflow/__init__.py
flatflow/py.typed
flatflow/megatron/__init__.py
flatflow/megatron/core/__init__.py
flatflow/megatron/core/pipeline_parallel/__init__.py
flatflow/megatron/core/pipeline_parallel/schedules.py
flatflow/nemo/__init__.py
flatflow/nemo/collections/__init__.py
flatflow/nemo/collections/nlp/__init__.py
flatflow/nemo/collections/nlp/data/__init__.py
flatflow/nemo/collections/nlp/data/language_modeling/__init__.py
flatflow/nemo/collections/nlp/data/language_modeling/megatron/__init__.py
flatflow/nemo/collections/nlp/data/language_modeling/megatron/blendable_dataset.py
flatflow/nemo/collections/nlp/data/language_modeling/megatron/data_samplers.py
flatflow/nemo/collections/nlp/data/language_modeling/megatron/gpt_dataset.py
flatflow/nemo/collections/nlp/data/language_modeling/megatron/gpt_sft_chat_dataset.py
flatflow/nemo/collections/nlp/data/language_modeling/megatron/gpt_sft_dataset.py
flatflow/nemo/collections/nlp/data/language_modeling/megatron/megatron_batch_samplers.py
flatflow/nemo/collections/nlp/data/language_modeling/megatron/obfd_dataset.py
flatflow/nemo/collections/nlp/models/__init__.py
flatflow/nemo/collections/nlp/models/language_modeling/__init__.py
flatflow/nemo/collections/nlp/models/language_modeling/megatron_base_model.py
flatflow/nemo/collections/nlp/models/language_modeling/megatron_gpt_model.py
flatflow/nemo/collections/nlp/models/language_modeling/megatron_gpt_sft_model.py
flatflow/nemo/collections/nlp/modules/__init__.py
flatflow/nemo/collections/nlp/modules/common/__init__.py
flatflow/nemo/collections/nlp/modules/common/megatron/__init__.py
flatflow/nemo/collections/nlp/modules/common/megatron/megatron_init.py
flatflow/nemo/collections/nlp/parts/__init__.py
flatflow/nemo/collections/nlp/parts/megatron_trainer_builder.py
flatflow/nemo/collections/nlp/parts/nlp_overrides.py
flatflow/nemo/core/__init__.py
flatflow/nemo/core/classes/__init__.py
flatflow-0.0.62.dist-info/METADATA
flatflow-0.0.62.dist-info/WHEEL
flatflow-0.0.62.dist-info/top_level.txt
flatflow-0.0.62.dist-info/RECORD
flatflow-0.0.62.dist-info/licenses/LICENSE
flatflow-0.0.62.dist-info/sboms/auditwheel.cdx.json
