Metadata-Version: 2.4
Name: flatflow
Version: 0.0.62
Summary: Fast and exact parallel training of neural networks
Home-page: https://github.com/9rum/flatflow
Author: The FlatFlow Authors
License: Apache-2.0
Classifier: Programming Language :: C++
Classifier: Programming Language :: Python :: 3
Classifier: Programming Language :: Python :: 3.10
Classifier: Programming Language :: Python :: 3.11
Classifier: Programming Language :: Python :: 3.12
Classifier: Programming Language :: Python :: 3.13
Classifier: Programming Language :: Python :: 3.14
Classifier: Topic :: Scientific/Engineering :: Artificial Intelligence
Requires-Python: >=3.10
License-File: LICENSE
Requires-Dist: flatbuffers==24.12.23
Requires-Dist: grpcio==1.67.1
Requires-Dist: numpy
Dynamic: author
Dynamic: classifier
Dynamic: description-content-type
Dynamic: home-page
Dynamic: license
Dynamic: license-file
Dynamic: requires-dist
Dynamic: requires-python
Dynamic: summary
